odoo10_addon_l10n_si_upgraded-10.0.1.0.0.99.dev1-py2.7-nspkg.pth
odoo/addons/l10n_si_upgraded/README.rst
odoo/addons/l10n_si_upgraded/__init__.py
odoo/addons/l10n_si_upgraded/__manifest__.py
odoo/addons/l10n_si_upgraded/data/account.account.tag.csv
odoo/addons/l10n_si_upgraded/data/account.account.template.csv
odoo/addons/l10n_si_upgraded/data/account.chart.template.csv
odoo/addons/l10n_si_upgraded/data/account.fiscal.position.account.template.csv
odoo/addons/l10n_si_upgraded/data/account.fiscal.position.account.template.xml
odoo/addons/l10n_si_upgraded/data/account.fiscal.position.tax.template.csv
odoo/addons/l10n_si_upgraded/data/account.fiscal.position.tax.template.xml
odoo/addons/l10n_si_upgraded/data/account.fiscal.position.template.csv
odoo/addons/l10n_si_upgraded/data/account.fiscal.position.template.xml
odoo/addons/l10n_si_upgraded/data/account.tax.template.csv
odoo/addons/l10n_si_upgraded/data/account_chart_template_data.yml
odoo/addons/l10n_si_upgraded/data/l10n_si_chart_data.xml
odoo/addons/l10n_si_upgraded/data/res.bank.xml
odoo/addons/l10n_si_upgraded/static/description/icon.png
odoo10_addon_l10n_si_upgraded-10.0.1.0.0.99.dev1.dist-info/DESCRIPTION.rst
odoo10_addon_l10n_si_upgraded-10.0.1.0.0.99.dev1.dist-info/METADATA
odoo10_addon_l10n_si_upgraded-10.0.1.0.0.99.dev1.dist-info/RECORD
odoo10_addon_l10n_si_upgraded-10.0.1.0.0.99.dev1.dist-info/WHEEL
odoo10_addon_l10n_si_upgraded-10.0.1.0.0.99.dev1.dist-info/metadata.json
odoo10_addon_l10n_si_upgraded-10.0.1.0.0.99.dev1.dist-info/namespace_packages.txt
odoo10_addon_l10n_si_upgraded-10.0.1.0.0.99.dev1.dist-info/top_level.txt
